{
  "items": [
    {
      "tags": ["wildfly"],
      "owner": {
        "account_id": 8338753,
        "reputation": 21,
        "user_id": 6264734,
        "user_type": "registered",
        "profile_image": "https://www.gravatar.com/avatar/207910766883d8a2611ffc5479bd3e2f?s=256&d=identicon&r=PG",
        "display_name": "Senthil kumar",
        "link": "https://stackoverflow.com/users/6264734/senthil-kumar"
      },
      "is_answered": true,
      "view_count": 1210,
      "answer_count": 1,
      "score": 1,
      "last_activity_date": 1495632747,
      "creation_date": 1495630114,
      "question_id": 44158878,
      "content_license": "CC BY-SA 3.0",
      "link": "https://stackoverflow.com/questions/44158878/adding-a-module-in-wildfly-common-for-all-the-wars",
      "title": "Adding a module in wildfly common for all the wars"
    },
    {
      "tags": ["mariadb"],
      "owner": {
        "account_id": 8338753,
        "reputation": 21,
        "user_id": 6264734,
        "user_type": "registered",
        "profile_image": "https://www.gravatar.com/avatar/207910766883d8a2611ffc5479bd3e2f?s=256&d=identicon&r=PG",
        "display_name": "Senthil kumar",
        "link": "https://stackoverflow.com/users/6264734/senthil-kumar"
      },
      "is_answered": false,
      "view_count": 613,
      "answer_count": 1,
      "score": 0,
      "last_activity_date": 1486314789,
      "creation_date": 1461818121,
      "last_edit_date": 1461818486,
      "question_id": 36905334,
      "content_license": "CC BY-SA 3.0",
      "link": "https://stackoverflow.com/questions/36905334/slient-maria-db-install-is-not-working",
      "title": "Slient Maria DB Install is not working"
    },
    {
      "tags": ["wildfly", "drools"],
      "owner": {
        "account_id": 8338753,
        "reputation": 21,
        "user_id": 6264734,
        "user_type": "registered",
        "profile_image": "https://www.gravatar.com/avatar/207910766883d8a2611ffc5479bd3e2f?s=256&d=identicon&r=PG",
        "display_name": "Senthil kumar",
        "link": "https://stackoverflow.com/users/6264734/senthil-kumar"
      },
      "is_answered": false,
      "view_count": 353,
      "answer_count": 0,
      "score": 0,
      "last_activity_date": 1495617661,
      "creation_date": 1495539755,
      "last_edit_date": 1495617661,
      "question_id": 44133871,
      "content_license": "CC BY-SA 3.0",
      "link": "https://stackoverflow.com/questions/44133871/drools-on-wildfly-is-not-working",
      "title": "drools on wildfly is not working"
    },
    {
      "tags": ["wildfly"],
      "owner": {
        "account_id": 8338753,
        "reputation": 21,
        "user_id": 6264734,
        "user_type": "registered",
        "profile_image": "https://www.gravatar.com/avatar/207910766883d8a2611ffc5479bd3e2f?s=256&d=identicon&r=PG",
        "display_name": "Senthil kumar",
        "link": "https://stackoverflow.com/users/6264734/senthil-kumar"
      },
      "is_answered": true,
      "view_count": 970,
      "answer_count": 1,
      "score": 0,
      "last_activity_date": 1497003623,
      "creation_date": 1496130836,
      "last_edit_date": 1496133471,
      "question_id": 44256586,
      "content_license": "CC BY-SA 3.0",
      "link": "https://stackoverflow.com/questions/44256586/xml-api-jar-issue-in-wildfly-module-loading-precedence",
      "title": "xml-api jar issue in wildfly - module loading precedence"
    },
    {
      "tags": ["wildfly-8"],
      "owner": {
        "account_id": 8338753,
        "reputation": 21,
        "user_id": 6264734,
        "user_type": "registered",
        "profile_image": "https://www.gravatar.com/avatar/207910766883d8a2611ffc5479bd3e2f?s=256&d=identicon&r=PG",
        "display_name": "Senthil kumar",
        "link": "https://stackoverflow.com/users/6264734/senthil-kumar"
      },
      "is_answered": false,
      "view_count": 359,
      "answer_count": 1,
      "score": 0,
      "last_activity_date": 1677361601,
      "creation_date": 1498029104,
      "question_id": 44669138,
      "content_license": "CC BY-SA 3.0",
      "link": "https://stackoverflow.com/questions/44669138/extension-vs-global-modules-in-wildfly",
      "title": "extension vs global-modules in wildfly"
    },
    {
      "tags": ["liquibase"],
      "owner": {
        "account_id": 8338753,
        "reputation": 21,
        "user_id": 6264734,
        "user_type": "registered",
        "profile_image": "https://www.gravatar.com/avatar/207910766883d8a2611ffc5479bd3e2f?s=256&d=identicon&r=PG",
        "display_name": "Senthil kumar",
        "link": "https://stackoverflow.com/users/6264734/senthil-kumar"
      },
      "is_answered": false,
      "view_count": 188,
      "answer_count": 0,
      "score": 0,
      "last_activity_date": 1586246845,
      "creation_date": 1586187385,
      "last_edit_date": 1586246845,
      "question_id": 61063436,
      "content_license": "CC BY-SA 4.0",
      "link": "https://stackoverflow.com/questions/61063436/precondition-sqlcheck-is-not-working-for-schema",
      "title": "precondition &lt;sqlcheck&gt; is not working for schema"
    }
  ],
  "has_more": false,
  "quota_max": 300,
  "quota_remaining": 160
}
